setup.py
initclass_tamil/__init__.py
initclass_tamil.egg-info/PKG-INFO
initclass_tamil.egg-info/SOURCES.txt
initclass_tamil.egg-info/dependency_links.txt
initclass_tamil.egg-info/not-zip-safe
initclass_tamil.egg-info/top_level.txt