Metadata-Version: 1.0
Name: initclass-tamil
Version: 0.1
Summary: The init funtion
Home-page: http://github.com/storborg/funniest
Author: Flying Circus
Author-email: tamilvendanp@gmail.com
License: Grundfos
Platform: UNKNOWN
